[
  {
    "id": "cn01da01",
    "endonym": "北安",
    "exonym": "Bei'an"
  },
  {
    "id": "cn01da02",
    "endonym": "二井",
    "exonym": "Erjing"
  },
  {
    "id": "cn01da03",
    "endonym": "二龙山屯",
    "exonym": "Erlongshantun"
  },
  {
    "id": "cn01da04",
    "endonym": "五大连池",
    "exonym": "Wudalianchi"
  },
  {
    "id": "cn01da05",
    "endonym": "龙镇",
    "exonym": "Longzhen"
  },
  {
    "id": "cn01da06",
    "endonym": "襄河",
    "exonym": "Xianghe"
  },
  {
    "id": "cn01da07",
    "endonym": "龙门河",
    "exonym": "Longmenhe"
  },
  {
    "id": "cn01da08",
    "endonym": "辰清",
    "exonym": "Chenqing"
  },
  {
    "id": "cn01da09",
    "endonym": "清溪",
    "exonym": "Qingxi"
  },
  {
    "id": "cn01da0a",
    "endonym": "孙吴",
    "exonym": "Sunwu"
  },
  {
    "id": "cn01da0b",
    "endonym": "孙吴北",
    "exonym": "Sunwu North"
  },
  {
    "id": "cn01da0c",
    "endonym": "额雨",
    "exonym": "Eyu"
  },
  {
    "id": "cn01da0d",
    "endonym": "潮水",
    "exonym": "Chaoshui"
  },
  {
    "id": "cn01da0e",
    "endonym": "西岗子",
    "exonym": "Xigangzi"
  },
  {
    "id": "cn01da0f",
    "endonym": "三吉屯",
    "exonym": "Sanjitun"
  },
  {
    "id": "cn01da0g",
    "endonym": "锦河",
    "exonym": "Jinhe"
  },
  {
    "id": "cn01da0h",
    "endonym": "黑河",
    "exonym": "Heihe"
  }
]
