[
  {
    "id": "jp021j01",
    "endonym": "八戸",
    "exonym": "Hachinohe"
  },
  {
    "id": "jp021j02",
    "endonym": "長苗代",
    "exonym": "Naganawashiro"
  },
  {
    "id": "jp021j03",
    "endonym": "本八戸",
    "exonym": "Hon-Hachinohe"
  },
  {
    "id": "jp021j04",
    "endonym": "小中野",
    "exonym": "Konakano"
  },
  {
    "id": "jp021j05",
    "endonym": "陸奥湊",
    "exonym": "Mutsu-Minato"
  },
  {
    "id": "jp021j06",
    "endonym": "白銀",
    "exonym": "Shirogane"
  },
  {
    "id": "jp021j07",
    "endonym": "鮫",
    "exonym": "Same"
  },
  {
    "id": "jp021j08",
    "endonym": "陸奥白浜",
    "exonym": "Mutsu-Shirahama"
  },
  {
    "id": "jp021j09",
    "endonym": "種差海岸",
    "exonym": "Tanesashi-Kaigan"
  },
  {
    "id": "jp021j0a",
    "endonym": "大久喜",
    "exonym": "Okuki"
  },
  {
    "id": "jp021j0b",
    "endonym": "金浜",
    "exonym": "Kanehama"
  },
  {
    "id": "jp021j0c",
    "endonym": "大蛇",
    "exonym": "Oja"
  },
  {
    "id": "jp021j0d",
    "endonym": "階上",
    "exonym": "Hashikami"
  },
  {
    "id": "jp021j0e",
    "endonym": "角の浜",
    "exonym": "Kadonohama"
  },
  {
    "id": "jp021j0f",
    "endonym": "平内",
    "exonym": "Hiranai"
  },
  {
    "id": "jp021j0g",
    "endonym": "種市",
    "exonym": "Taneichi"
  },
  {
    "id": "jp021j0h",
    "endonym": "玉川",
    "exonym": "Tamagawa"
  },
  {
    "id": "jp021j0i",
    "endonym": "宿戸",
    "exonym": "Shukunohe"
  },
  {
    "id": "jp021j0j",
    "endonym": "陸中八木",
    "exonym": "Rikuchu-Yagi"
  },
  {
    "id": "jp021j0k",
    "endonym": "有家",
    "exonym": "Uge"
  },
  {
    "id": "jp021j0l",
    "endonym": "陸中中野",
    "exonym": "Rikuchu-Nakano"
  },
  {
    "id": "jp021j0m",
    "endonym": "侍浜",
    "exonym": "Samuraihama"
  },
  {
    "id": "jp021j0n",
    "endonym": "陸中夏井",
    "exonym": "Rikuchu-Natsui"
  },
  {
    "id": "jp021j0o",
    "endonym": "久慈",
    "exonym": "Kuji"
  }
]
