[
  {
    "id": "01",
    "endonym": "Hà Nội",
    "exonym": "Ha Noi"
  },
  {
    "id": "02",
    "endonym": "Long Biên",
    "exonym": "Long Bien"
  },
  {
    "id": "03",
    "endonym": "Gia Lâm",
    "exonym": "Gia Lam"
  },
  {
    "id": "04",
    "endonym": "Yên Viên",
    "exonym": "Yen Vien"
  },
  {
    "id": "05",
    "endonym": "Cổ Loa",
    "exonym": "Co Loa"
  },
  {
    "id": "06",
    "endonym": "Đông Anh",
    "exonym": "Dong Anh"
  },
  {
    "id": "07",
    "endonym": "Đa Phúc",
    "exonym": "Da Phuc"
  },
  {
    "id": "08",
    "endonym": "Trung Giã",
    "exonym": "Trung Gia"
  },
  {
    "id": "09",
    "endonym": "Phổ Yên",
    "exonym": "Pho Yen"
  },
  {
    "id": "0a",
    "endonym": "Lương Sơn",
    "exonym": "Luong Son"
  },
  {
    "id": "0b",
    "endonym": "Lưu Xá",
    "exonym": "Luu Xa"
  },
  {
    "id": "0c",
    "endonym": "Thái Nguyên",
    "exonym": "Thai Nguyen"
  },
  {
    "id": "0d",
    "endonym": "Quán Triều",
    "exonym": "Quan Trieu"
  }
]
