[
  {
    "id": "cn010x01",
    "endonym": "淄博",
    "exonym": "Zibo"
  },
  {
    "id": "cn010x02",
    "endonym": "杜科",
    "exonym": "Sheke"
  },
  {
    "id": "cn010x03",
    "endonym": "农中",
    "exonym": "Nongzhong"
  },
  {
    "id": "cn010x04",
    "endonym": "桓台",
    "exonym": "Huantai"
  },
  {
    "id": "cn010x05",
    "endonym": "曹王",
    "exonym": "Caowang"
  },
  {
    "id": "cn010x06",
    "endonym": "博兴",
    "exonym": "Boxing"
  },
  {
    "id": "cn010x07",
    "endonym": "纯化",
    "exonym": "Chunhua"
  },
  {
    "id": "cn010x08",
    "endonym": "史口",
    "exonym": "Shikou"
  },
  {
    "id": "cn010x09",
    "endonym": "东营",
    "exonym": "Dongying"
  }
]
