[
  {
    "id": "cn013l01",
    "endonym": "南昌西",
    "exonym": "Nanchang West"
  },
  {
    "id": "cn013l02",
    "endonym": "三江镇",
    "exonym": "Sanjiangzhen"
  },
  {
    "id": "cn013l03",
    "endonym": "大岗",
    "exonym": "Dagang"
  },
  {
    "id": "cn013l04",
    "endonym": "抚州北",
    "exonym": "Fuzhou North"
  },
  {
    "id": "cn013l05",
    "endonym": "抚州",
    "exonym": "Fuzhou"
  },
  {
    "id": "cn013l06",
    "endonym": "腾桥",
    "exonym": "Tengqiao"
  },
  {
    "id": "cn013l07",
    "endonym": "南城",
    "exonym": "Nancheng"
  },
  {
    "id": "cn013l08",
    "endonym": "南丰",
    "exonym": "Nanfeng"
  },
  {
    "id": "cn013l09",
    "endonym": "建宁县北",
    "exonym": "Jianningxian North"
  },
  {
    "id": "cn013l0a",
    "endonym": "泰宁",
    "exonym": "Taining"
  },
  {
    "id": "cn013l0b",
    "endonym": "将乐",
    "exonym": "Jiangle"
  },
  {
    "id": "cn013l0c",
    "endonym": "夏茂",
    "exonym": "Xiaomao"
  },
  {
    "id": "cn013l0d",
    "endonym": "三明北",
    "exonym": "Sanming North"
  },
  {
    "id": "cn013l0e",
    "endonym": "尤溪",
    "exonym": "Youxi"
  },
  {
    "id": "cn013l0f",
    "endonym": "中仙",
    "exonym": "Zhongxian"
  },
  {
    "id": "cn013l0g",
    "endonym": "长庆",
    "exonym": "Changqing"
  },
  {
    "id": "cn013l0h",
    "endonym": "永泰",
    "exonym": "Yongtai"
  },
  {
    "id": "cn013l0i",
    "endonym": "杜坞",
    "exonym": "Duwu"
  },
  {
    "id": "cn013l0j",
    "endonym": "福州",
    "exonym": "Fuzhou"
  }
]
