[
  {
    "id": "th010g01",
    "endonym": "วงเวียนใหญ่",
    "exonym": "Wongwian Yai"
  },
  {
    "id": "th010g02",
    "endonym": "ตลาดพลู",
    "exonym": "Talat Phlu"
  },
  {
    "id": "th010g03",
    "endonym": "คลองต้นไทร",
    "exonym": "Khlong Ton Sai"
  },
  {
    "id": "th010g04",
    "endonym": "จอมทอง",
    "exonym": "Chom Tong"
  },
  {
    "id": "th010g05",
    "endonym": "วัดไทร",
    "exonym": "Wat Sai"
  },
  {
    "id": "th010g06",
    "endonym": "วัดสิงห์",
    "exonym": "Wat Sing"
  },
  {
    "id": "th010g07",
    "endonym": "บางบอน",
    "exonym": "Bang Bon"
  },
  {
    "id": "th010g08",
    "endonym": "การเคหะธนบุรี",
    "exonym": "Khan Keha"
  },
  {
    "id": "th010g09",
    "endonym": "รางสะแก",
    "exonym": "Rang Sakae"
  },
  {
    "id": "th010g0a",
    "endonym": "รางโพธิ์",
    "exonym": "Rang Pho"
  },
  {
    "id": "th010g0b",
    "endonym": "สามแยก",
    "exonym": "Sam Yaek"
  },
  {
    "id": "th010g0c",
    "endonym": "พรมแดน",
    "exonym": "Phrom Daen"
  },
  {
    "id": "th010g0d",
    "endonym": "ทุ่งสีทอง",
    "exonym": "Thung Si Thong"
  },
  {
    "id": "th010g0e",
    "endonym": "บางน้ำจืด",
    "exonym": "Bang Nam Jued"
  },
  {
    "id": "th010g0f",
    "endonym": "คอกควาย",
    "exonym": "Khok Khwai"
  },
  {
    "id": "th010g0g",
    "endonym": "บ้านขอม",
    "exonym": "Ban Khom"
  },
  {
    "id": "th010g0h",
    "endonym": "คลองจาก",
    "exonym": "Khlong Chak"
  },
  {
    "id": "th010g0i",
    "endonym": "มหาชัย",
    "exonym": "Maha Chai"
  }
]
