[
  {
    "id": "01",
    "endonym": "宝積寺",
    "exonym": "Hoshakuji"
  },
  {
    "id": "02",
    "endonym": "下野花岡",
    "exonym": "Shimotsuke-Hanaoka"
  },
  {
    "id": "03",
    "endonym": "仁井田",
    "exonym": "Niita"
  },
  {
    "id": "04",
    "endonym": "鴻野山",
    "exonym": "Konoyama"
  },
  {
    "id": "05",
    "endonym": "大金",
    "exonym": "Ogane"
  },
  {
    "id": "06",
    "endonym": "小塙",
    "exonym": "Kobana"
  },
  {
    "id": "07",
    "endonym": "滝",
    "exonym": "Taki"
  },
  {
    "id": "08",
    "endonym": "烏山",
    "exonym": "Karasuyama"
  }
]
