[
  {
    "id": "cn012m01",
    "endonym": "宣城",
    "exonym": "Xuancheng"
  },
  {
    "id": "cn012m02",
    "endonym": "建国",
    "exonym": "Jianguo"
  },
  {
    "id": "cn012m03",
    "endonym": "十字铺",
    "exonym": "Shizipu"
  },
  {
    "id": "cn012m04",
    "endonym": "誓节渡",
    "exonym": "Shijiedu"
  },
  {
    "id": "cn012m05",
    "endonym": "广德",
    "exonym": "Guangde"
  },
  {
    "id": "cn012m06",
    "endonym": "泗安",
    "exonym": "Si'an"
  },
  {
    "id": "cn012m07",
    "endonym": "大云",
    "exonym": "Dayun"
  },
  {
    "id": "cn012m08",
    "endonym": "长兴南",
    "exonym": "Changxing South"
  },
  {
    "id": "cn012m09",
    "endonym": "湖州西",
    "exonym": "Huzhou West"
  },
  {
    "id": "cn012m0a",
    "endonym": "湖州",
    "exonym": "Huzhou"
  },
  {
    "id": "cn012m0b",
    "endonym": "妙西",
    "exonym": "Miaoxi"
  },
  {
    "id": "cn012m0c",
    "endonym": "梅峰",
    "exonym": "Meifeng"
  },
  {
    "id": "cn012m0d",
    "endonym": "德清西",
    "exonym": "Deqing West"
  },
  {
    "id": "cn012m0e",
    "endonym": "沈家塘",
    "exonym": "Shenjiatang"
  },
  {
    "id": "cn012m0f",
    "endonym": "星桥",
    "exonym": "Xingqiao"
  },
  {
    "id": "cn012m0g",
    "endonym": "乔司",
    "exonym": "Qiaosi"
  },
  {
    "id": "cn012m0h",
    "endonym": "杭州",
    "exonym": "Hangzhou"
  }
]
