[
  {
    "id": "jp022201",
    "endonym": "豊野",
    "exonym": "Toyono"
  },
  {
    "id": "jp022202",
    "endonym": "信濃浅野",
    "exonym": "Shinano-Asano"
  },
  {
    "id": "jp022203",
    "endonym": "立ヶ花",
    "exonym": "Tategahana"
  },
  {
    "id": "jp022204",
    "endonym": "上今井",
    "exonym": "Kamiimai"
  },
  {
    "id": "jp022205",
    "endonym": "替佐",
    "exonym": "Kaesa"
  },
  {
    "id": "jp022206",
    "endonym": "蓮",
    "exonym": "Hachisu"
  },
  {
    "id": "jp022207",
    "endonym": "飯山",
    "exonym": "Iiyama"
  },
  {
    "id": "jp022208",
    "endonym": "北飯山",
    "exonym": "Kita-Iiyama"
  },
  {
    "id": "jp022209",
    "endonym": "信濃平",
    "exonym": "Shinano-Taira"
  },
  {
    "id": "jp02220a",
    "endonym": "戸狩野沢温泉",
    "exonym": "Togari-Nozawaonsen"
  },
  {
    "id": "jp02220b",
    "endonym": "上境",
    "exonym": "Kamisakai"
  },
  {
    "id": "jp02220c",
    "endonym": "上桑名川",
    "exonym": "Kami-Kuwanagawa"
  },
  {
    "id": "jp02220d",
    "endonym": "桑名川",
    "exonym": "Kuwanagawa"
  },
  {
    "id": "jp02220e",
    "endonym": "西大滝",
    "exonym": "Nishi-Otaki"
  },
  {
    "id": "jp02220f",
    "endonym": "信濃白鳥",
    "exonym": "Shinano-Shiratori"
  },
  {
    "id": "jp02220g",
    "endonym": "平滝",
    "exonym": "Hirataki"
  },
  {
    "id": "jp02220h",
    "endonym": "横倉",
    "exonym": "Yokokura"
  },
  {
    "id": "jp02220i",
    "endonym": "森宮野原",
    "exonym": "Mori-Miyanohara"
  },
  {
    "id": "jp02220j",
    "endonym": "足滝",
    "exonym": "Ashidaki"
  },
  {
    "id": "jp02220k",
    "endonym": "越後田中",
    "exonym": "Echigo-Tanaka"
  },
  {
    "id": "jp02220l",
    "endonym": "津南",
    "exonym": "Tsunan"
  },
  {
    "id": "jp02220m",
    "endonym": "越後鹿渡",
    "exonym": "Echigo-Shikawatari"
  },
  {
    "id": "jp02220n",
    "endonym": "越後田沢",
    "exonym": "Echigo-Tazawa"
  },
  {
    "id": "jp02220o",
    "endonym": "越後水沢",
    "exonym": "Echigo-Mizusawa"
  },
  {
    "id": "jp02220p",
    "endonym": "土市",
    "exonym": "Doichi"
  },
  {
    "id": "jp02220q",
    "endonym": "十日町",
    "exonym": "Tokamachi"
  },
  {
    "id": "jp02220r",
    "endonym": "魚沼中条",
    "exonym": "Uonuma-Nakajo"
  },
  {
    "id": "jp02220s",
    "endonym": "下条",
    "exonym": "Gejo"
  },
  {
    "id": "jp02220t",
    "endonym": "越後岩沢",
    "exonym": "Echigo-Iwasawa"
  },
  {
    "id": "jp02220u",
    "endonym": "内ヶ巻",
    "exonym": "Uchigamaki"
  },
  {
    "id": "jp02220v",
    "endonym": "越後川口",
    "exonym": "Echigo-Kawaguchi"
  }
]
